compress/__init__.py
compress/__main__.py
compress/core.py
compress/main.py
compress/setup.py
unirock_compress-0.1.0.dist-info/METADATA
unirock_compress-0.1.0.dist-info/WHEEL
unirock_compress-0.1.0.dist-info/RECORD
