Metadata-Version: 2.1
Name: unirock-compress
Version: 0.1.0
Summary: 
Author: kiortir
Author-email: kiortir@yandex.ru
Requires-Python: >=3.11,<4.0
Classifier: Programming Language :: Python :: 3
Classifier: Programming Language :: Python :: 3.11
Classifier: Programming Language :: Python :: 3.12
Requires-Dist: mozjpeg-lossless-optimization (==1.1.3)
Requires-Dist: pillow (==10.2.0)
